{
  "dependencies": {
    "identityapp1": {
      "ignored": "true",
      "suggestion": "true",
      "type": "identityapp",
      "connectionId": ""
    },
    "mssql2": {
      "secretStore": "AzureAppSettings",
      "resourceId": "/subscriptions/[parameters('subscriptionId')]/resourcegroups/[parameters('resourceGroupName')]/providers/Microsoft.Sql/servers/oedbserver/databases/OE_db",
      "type": "mssql.azure",
      "connectionId": "Kestrel:Certificates:Development:Password"
    },
    "mssql1": {
      "secretStore": "AzureAppSettings",
      "resourceId": "/subscriptions/[parameters('subscriptionId')]/resourceGroups/[parameters('resourceGroupName')]/providers/Microsoft.Sql/servers/oedbserver/databases/OE_db",
      "type": "mssql.azure",
      "connectionId": "ConnectionStrings:OEDBCS"
    }
  }
}